examples/__init__.py
examples/client.py
examples/clientGui.py
examples/server.py
examples/serverGui.py
pyRpc/__init__.py
pyRpc/_version.py
pyRpc/client.py
pyRpc/constants.py
pyRpc/server.py
pyRpc-0.4.0.dist-info/LICENSE.TXT
pyRpc-0.4.0.dist-info/METADATA
pyRpc-0.4.0.dist-info/WHEEL
pyRpc-0.4.0.dist-info/top_level.txt
pyRpc-0.4.0.dist-info/RECORD
