Metadata-Version: 2.1
Name: pyRpc
Version: 0.4.0
Summary: A simple remote procedure call module using ZeroMQ
Home-page: https://github.com/justinfx/pyRpc
Author: Justin Israel
Author-email: justinisrael@gmail.com
License: BSD
Platform: UNKNOWN
Classifier: Development Status :: 3 - Alpha
Classifier: Intended Audience :: Developers
Classifier: License :: OSI Approved :: BSD License
Classifier: Operating System :: OS Independent
Classifier: Programming Language :: Python
Classifier: Programming Language :: Python :: 2
Classifier: Programming Language :: Python :: 3
Classifier: Topic :: Communications
Requires-Dist: pyzmq
